refextract/__init__.py
refextract/authors/__init__.py
refextract/authors/regexs.py
refextract/config.cfg
refextract/documents/__init__.py
refextract/documents/pdf.py
refextract/documents/text.py
refextract/extract.py
refextract/references/__init__.py
refextract/references/api.py
refextract/references/config.py
refextract/references/engine.py
refextract/references/errors.py
refextract/references/find.py
refextract/references/kbs/authors.kb
refextract/references/kbs/books.kb
refextract/references/kbs/collaborations.kb
refextract/references/kbs/journal-titles-re.kb
refextract/references/kbs/journal-titles.kb
refextract/references/kbs/publishers.kb
refextract/references/kbs/report-numbers.kb
refextract/references/kbs/special-journals.kb
refextract/references/kbs.py
refextract/references/pdf.py
refextract/references/record.py
refextract/references/regexs.py
refextract/references/tag.py
refextract/references/text.py
refextract-1.1.6.dist-info/METADATA
refextract-1.1.6.dist-info/WHEEL
refextract-1.1.6.dist-info/licenses/LICENSE
refextract-1.1.6.dist-info/RECORD
