Metadata-Version: 2.4
Name: refextract
Version: 1.1.6
Summary: Small library for extracting references used in scholarly communication.
License: GPL-2.0-or-later
License-File: LICENSE
Author: CERN
Author-email: admin@inspirehep.net
Requires-Python: >=3.11,<4
Classifier: Development Status :: 4 - Beta
Classifier: Environment :: Console
Classifier: Intended Audience :: Developers
Classifier: Intended Audience :: Science/Research
Classifier: License :: OSI Approved :: GNU General Public License v2 (GPLv2)
Classifier: License :: OSI Approved :: GNU General Public License v2 or later (GPLv2+)
Classifier: Operating System :: OS Independent
Classifier: Programming Language :: Python
Classifier: Programming Language :: Python :: 3
Classifier: Programming Language :: Python :: 3.11
Classifier: Programming Language :: Python :: 3.12
Classifier: Programming Language :: Python :: 3.13
Classifier: Programming Language :: Python :: 3.14
Classifier: Programming Language :: Python :: 3.6
Classifier: Programming Language :: Python :: 3.7
Classifier: Programming Language :: Python :: 3.8
Classifier: Topic :: Scientific/Engineering :: Information Analysis
Classifier: Topic :: Software Development :: Libraries
Classifier: Topic :: Software Development :: Libraries :: Python Modules
Classifier: Topic :: Utilities
Requires-Dist: inspire-utils (>=3.0.61,<4.0.0)
Requires-Dist: pypdf (>=5.4.0,<6.0.0)
Requires-Dist: python-magic (>=0.4.27,<0.5.0)
Requires-Dist: requests (>=2.32.3,<3.0.0)
Requires-Dist: unidecode (>=1.0.22,<2.0)
Project-URL: Homepage, https://github.com/inspirehep/refextract
